{
	"configurations" : 
	[
		{
			"directories" : 
			[
				{
					"build" : ".",
					"jsonFile" : "directory-.-Debug-f5ebdc15457944623624.json",
					"minimumCMakeVersion" : 
					{
						"string" : "3.14"
					},
					"projectIndex" : 0,
					"source" : ".",
					"targetIndexes" : 
					[
						0
					]
				}
			],
			"name" : "Debug",
			"projects" : 
			[
				{
					"directoryIndexes" : 
					[
						0
					],
					"name" : "fsoft2026_1DB_2",
					"targetIndexes" : 
					[
						0
					]
				}
			],
			"targets" : 
			[
				{
					"directoryIndex" : 0,
					"id" : "fsoft2026_1DB_2::@6890427a1f51a3e7e1df",
					"jsonFile" : "target-fsoft2026_1DB_2-Debug-62cde764134de66c9a5f.json",
					"name" : "fsoft2026_1DB_2",
					"projectIndex" : 0
				}
			]
		}
	],
	"kind" : "codemodel",
	"paths" : 
	{
		"build" : "/home/diogosilva/CLionProjects/fsoft2026_1DB_2/Project/cmake-build-debug",
		"source" : "/home/diogosilva/CLionProjects/fsoft2026_1DB_2/Project"
	},
	"version" : 
	{
		"major" : 2,
		"minor" : 8
	}
}
